fast_forward_job_hunting-0.0.4.data/data/share/applications/zamestnani.desktop
zamestnani/__main__.py
zamestnani/applications_reported.mp3
zamestnani/applications_sent.mp3
zamestnani/centrala.glade
zamestnani/centrala.py
zamestnani/cv.db
zamestnani/cv.py
zamestnani/cv_automat.py
zamestnani/logo.png
zamestnani/selen.py
zamestnani/selen_zamestnani.py
zamestnani/selen_zamestnani_orig.py
zamestnani/spousteni.py
zamestnani/terms_conditions.pdf
zamestnani/zamestnani.db
zamestnani/zamestnani.desktop
zamestnani/zaplat_registraci.pdf
fast_forward_job_hunting-0.0.4.dist-info/LICENSE
fast_forward_job_hunting-0.0.4.dist-info/METADATA
fast_forward_job_hunting-0.0.4.dist-info/WHEEL
fast_forward_job_hunting-0.0.4.dist-info/entry_points.txt
fast_forward_job_hunting-0.0.4.dist-info/top_level.txt
fast_forward_job_hunting-0.0.4.dist-info/RECORD
