Metadata-Version: 2.1
Name: fast-forward-job-hunting
Version: 0.0.4
Summary: Fast Forward Job Hunting speeds up your job seeking efforts. It saves your time and helps you into employment significantly faster.
Home-page: UNKNOWN
Author: Legal Machinery
Author-email: kilodeltalima@mail.ru
License: Proprietary
Keywords: job,jobseeker,cv,resume,curriculum,vitae,employment,employee
Platform: UNKNOWN
Classifier: Topic :: Utilities
Classifier: Topic :: Other/Nonlisted Topic
Classifier: Development Status :: 3 - Alpha
Classifier: License :: Other/Proprietary License
Classifier: Operating System :: POSIX :: Linux
Classifier: Environment :: X11 Applications :: GTK
Classifier: Intended Audience :: End Users/Desktop
Classifier: Natural Language :: English
Classifier: Programming Language :: Python :: 3.7
Requires-Python: >=3.7
License-File: LICENSE
Requires-Dist: PyGObject
Requires-Dist: keyring
Requires-Dist: nltk
Requires-Dist: pyperclip
Requires-Dist: selenium
Requires-Dist: scikit-learn
